dimtributor/.DS_Store
dimtributor/__init__.py
dimtributor/tree.py
dimtributor-0.0.3.dist-info/METADATA
dimtributor-0.0.3.dist-info/WHEEL
dimtributor-0.0.3.dist-info/licenses/LICENSE
dimtributor-0.0.3.dist-info/RECORD
