Metadata-Version: 2.1
Name: dimtributor
Version: 0.0.3
Summary: a python package for automatical dimension attribution
Project-URL: Homepage, https://github.com/wronganswer/dimtributor
Project-URL: Bug Tracker, https://github.com/wronganswer/dimtributor/issues
Author-email: kennyzhang <124466529@qq.com>
License-File: LICENSE
Classifier: License :: OSI Approved :: MIT License
Classifier: Operating System :: OS Independent
Classifier: Programming Language :: Python :: 3
Requires-Python: >=3.7
